bluecore/models/__init__.py
bluecore/models/base.py
bluecore/models/bf_classes.py
bluecore/models/instance.py
bluecore/models/other_resource.py
bluecore/models/resource.py
bluecore/models/version.py
bluecore/models/work.py
bluecore/utils/graph.py
blue_core_data_models-0.2.0.dist-info/METADATA
blue_core_data_models-0.2.0.dist-info/WHEEL
blue_core_data_models-0.2.0.dist-info/top_level.txt
blue_core_data_models-0.2.0.dist-info/RECORD
