Metadata-Version: 2.2
Name: blue-core-data-models
Version: 0.2.0
Summary: Blue Core BIBFRAME Data Models
Requires-Python: >=3.12
Requires-Dist: alembic>=1.14.1
Requires-Dist: psycopg2-binary>=2.9.10
Requires-Dist: rdflib>=7.1.3
